README.md
setup.py
pulumiverse_statuscake/__init__.py
pulumiverse_statuscake/_inputs.py
pulumiverse_statuscake/_utilities.py
pulumiverse_statuscake/contact_group.py
pulumiverse_statuscake/get_contact_group.py
pulumiverse_statuscake/get_pagespeed_monitoring_locations.py
pulumiverse_statuscake/get_statuscake_contact_group.py
pulumiverse_statuscake/get_statuscake_pagespeed_monitoring_locations.py
pulumiverse_statuscake/get_statuscake_uptime_monitoring_locations.py
pulumiverse_statuscake/get_uptime_monitoring_locations.py
pulumiverse_statuscake/maintenance_window.py
pulumiverse_statuscake/outputs.py
pulumiverse_statuscake/pagespeed_check.py
pulumiverse_statuscake/provider.py
pulumiverse_statuscake/pulumi-plugin.json
pulumiverse_statuscake/py.typed
pulumiverse_statuscake/ssl_check.py
pulumiverse_statuscake/statuscake_contact_group.py
pulumiverse_statuscake/statuscake_maintenance_window.py
pulumiverse_statuscake/statuscake_pagespeed_check.py
pulumiverse_statuscake/statuscake_ssl_check.py
pulumiverse_statuscake/statuscake_uptime_check.py
pulumiverse_statuscake/uptime_check.py
pulumiverse_statuscake.egg-info/PKG-INFO
pulumiverse_statuscake.egg-info/SOURCES.txt
pulumiverse_statuscake.egg-info/dependency_links.txt
pulumiverse_statuscake.egg-info/not-zip-safe
pulumiverse_statuscake.egg-info/requires.txt
pulumiverse_statuscake.egg-info/top_level.txt
pulumiverse_statuscake/config/__init__.py
pulumiverse_statuscake/config/vars.py