Metadata-Version: 2.1
Name: pulumiverse-statuscake
Version: 1.0.2
Summary: A Pulumi package for creating and managing Statuscake resources.
Home-page: https://github.com/pulumiverse
License: Apache-2.0
Project-URL: Repository, https://github.com/pulumiverse/pulumi-statuscake
Keywords: pulumi statuscake category/cloud
Platform: UNKNOWN
